countmytokens/__init__.py
countmytokens/main.py
countmytokens-0.1.1.dist-info/LICENSE
countmytokens-0.1.1.dist-info/METADATA
countmytokens-0.1.1.dist-info/WHEEL
countmytokens-0.1.1.dist-info/entry_points.txt
countmytokens-0.1.1.dist-info/top_level.txt
countmytokens-0.1.1.dist-info/RECORD
