Metadata-Version: 2.2
Name: countmytokens
Version: 0.1.1
Summary: Count tokens in dir or git repos
Requires-Python: >=3.12
License-File: LICENSE
Requires-Dist: aiofiles>=24.1.0
Requires-Dist: build>=1.2.2.post1
Requires-Dist: gitpython>=3.1.44
Requires-Dist: tiktoken>=0.8.0
Requires-Dist: treelib>=1.7.0
Provides-Extra: dev
Requires-Dist: pytest>=7.4.0; extra == "dev"
Requires-Dist: pytest-cov>=4.1.0; extra == "dev"
Requires-Dist: ruff>=0.9.3; extra == "dev"
Requires-Dist: black>=24.1.1; extra == "dev"
Requires-Dist: mypy>=1.8.0; extra == "dev"
